gdsfill/__init__.py
gdsfill/gdsfill.py
gdsfill/library/__init__.py
gdsfill/library/common.py
gdsfill/library/fill.py
gdsfill/library/klayout.py
gdsfill/library/filler/__init__.py
gdsfill/library/filler/helper.py
gdsfill/library/filler/overlap.py
gdsfill/library/filler/square.py
gdsfill/library/filler/track.py
gdsfill-0.1.2.dist-info/licenses/LICENSE
gdsfill-0.1.2.dist-info/METADATA
gdsfill-0.1.2.dist-info/WHEEL
gdsfill-0.1.2.dist-info/entry_points.txt
gdsfill-0.1.2.dist-info/top_level.txt
gdsfill-0.1.2.dist-info/RECORD
