Metadata-Version: 2.4
Name: gdsfill
Version: 0.1.2
Summary: Open-source tool for inserting dummy metal fill into semiconductor layouts.
Author-email: Daniel Schultz <dnltz@aesc-silicon.de>
License-Expression: LGPL-2.1-or-later
Project-URL: Homepage, https://github.com/aesc-silicon/gdsfill
Project-URL: Issues, https://github.com/aesc-silicon/gdsfill/issues
Classifier: Intended Audience :: Developers
Classifier: Development Status :: 3 - Alpha
Classifier: Operating System :: POSIX :: Linux
Classifier: Programming Language :: Python :: 3 :: Only
Classifier: Programming Language :: Python :: 3.9
Classifier: Programming Language :: Python :: 3.10
Classifier: Programming Language :: Python :: 3.11
Requires-Python: >=3.9
License-File: LICENSE
Requires-Dist: pyyaml
Requires-Dist: packaging
Requires-Dist: gdstk
Requires-Dist: rich
Dynamic: license-file
